fuzz_craft/__init__.py
fuzz_craft/__main__.py
fuzz_craft/cli.py
fuzz_craft/codeql.py
fuzz_craft/commands/__init__.py
fuzz_craft/commands/create_database.py
fuzz_craft/commands/create_harness.py
fuzz_craft/commands/create_llm_harness.py
fuzz_craft/constants.py
fuzz_craft/exceptions.py
fuzz_craft/file_manager.py
fuzz_craft/file_processor.py
fuzz_craft/fuzzers/__init__.py
fuzz_craft/fuzzers/atheris.py
fuzz_craft/fuzzers/libfuzzer.py
fuzz_craft/harness.py
fuzz_craft/log.py
fuzz_craft/ql/c-cpp/codeql-pack.lock.yml
fuzz_craft/ql/c-cpp/function.ql
fuzz_craft/ql/c-cpp/qlpack.yml
fuzz_craft/ql/python/codeql-pack.lock.yml
fuzz_craft/ql/python/function.ql
fuzz_craft/ql/python/qlpack.yml
fuzz_craft/targets.py
fuzz_craft/template.py
fuzz_craft/templates/c_cpp_libfuzzer.jinja
fuzz_craft/templates/c_cpp_shared_libfuzzer.jinja
fuzz_craft/templates/libfuzzer.jinja
fuzz_craft/templates/py_atheris.jinja
fuzz_craft/utils.py
fuzz_craft-0.0.2.dist-info/LICENSE
fuzz_craft-0.0.2.dist-info/METADATA
fuzz_craft-0.0.2.dist-info/WHEEL
fuzz_craft-0.0.2.dist-info/RECORD
